Workbook

Sheet Dashboard
B2: A.G. BARR p.l.c. (LON:BAG) - Equity Trade Idea
B3: Prepared by Jewel Thomas | Consumer Staples / Soft Drinks | Data as of 30 Jun 2026 | Directional view, data-driven
B5: SHARE PRICE | F5: PRICE TARGET | J5: RATING | N5: EV / EBITDA | Y5: 8.7x | Z5: =Valuation!D21 -> 699.82594
B6: =Valuation!B3 -> 632 | F6: =Valuation!B29 -> 785 | J6: BUY | N6: =Valuation!B11 -> 8.704973 | Y6: 10.0x | Z6: =Valuation!D22 -> 793.73368
B7: as of 30 Jun 2026 | F7: =Valuation!B29/Valuation!B3-1 -> 0.24208861 | J7: 12-month horizon | N7: vs ~13x Britvic take-out | Y7: 11.0x | Z7: =Valuation!D23 -> 865.97041
Y8: 13.0x | Z8: =Valuation!D24 -> 1010.4439
B9: IMPLIED VALUE / SHARE vs EV/EBITDA MULTIPLE (FY27E) | J9: VALUATION SNAPSHOT
J11: Share price (p) | O11: =Valuation!B3 -> 632
J12: Price target (p) | O12: =Valuation!B29 -> 785
J13: Upside | O13: =Valuation!B29/Valuation!B3-1 -> 0.24208861
J14: Market cap | O14: =Valuation!B5 -> 726.168
J15: Net cash | O15: =-Valuation!B6 -> 82
J16: EV / FY26 EBITDA | O16: =Valuation!B11 -> 8.704973
J17: P/E (statutory) | O17: =Valuation!B13 -> 15.41758
J18: Dividend yield | O18: =Valuation!B14 -> 0.030063291
J19: Consensus | O19: Strong Buy ~784p
B26: THESIS: Net-cash, double-digit-growth soft-drinks brand (IRN-BRU, Rubicon, Boost) at 8.7x EV/EBITDA - a discount to its growth and to the ~13x Britvic take-out. Re-rating to 10x FY27E EBITDA implies ~794p. Full thesis, catalysts and risks on the 'Thesis & Risks' tab.

Sheet Read Me
B2: A.G. BARR p.l.c. (LON:BAG)
B3: Equity Trade Idea
B4: Prepared by Jewel Thomas | Portfolio analysis | Consumer Staples / Soft Drinks | Data as of 30 Jun 2026
B6: RECOMMENDATION
B7: BUY. Price target 785p vs 632p spot = c.24% upside over 12 months. A branded, net-cash, double-digit-growth soft-drinks business trading at only 8.7x EV/EBITDA - a discount to both its own growth and to sector M&A multiples.
B9: THE VIEW IN ONE LINE
B10: The market is pricing A.G. Barr as an ex-growth staple; the FY26 numbers (net income +19%, margin +120bps) and management's low-double-digit revenue guidance say otherwise. A modest re-rating toward peers closes the gap.
B12: WHY IT'S MISPRICED
B13: (1) EV/EBITDA 8.7x vs the ~13x Carlsberg paid for Britvic in 2024. (2) Net cash of ~GBP 82m (c.11% of market cap) de-risks the balance sheet and funds buybacks/M&A. (3) Consensus is Strong Buy (8 buy / 1 hold / 0 sell, target ~784p) yet the shares still trade on a sub-market multiple.
B15: DATA INTEGRITY
B16: Every figure is reported/market-sourced (see 'Valuation' tab comments). The price target is derived transparently: FY27E EBITDA of ~GBP 83m at a 10x EV/EBITDA multiple plus net cash. The multiple-sensitivity grid shows the call is robust - even at 8.7x on FY27 numbers the stock is worth ~700p.
B18: KEY RISKS
... B25: For portfolio / educational purposes only. Not investment advice; not affiliated with or endorsed by A.G. Barr p.l.c. A personal directional view for demonstration of equity analysis.

Sheet Valuation
A1: VALUATION (GBP m unless stated)
A3: Share price (p) | B3: 632
A4: Shares in issue (m) | B4: 114.9
A5: Market capitalisation | B5: =B3/100*B4 -> 726.168
A6: Less: net cash | B6: -82
A7: Enterprise value (EV) | B7: =B5+B6 -> 644.168
A9: FY26 revenue | B9: 437.3
A10: FY26 EBITDA (est.) | B10: 74
A11: EV / FY26 EBITDA | B11: =B7/B10 -> 8.704973
A12: FY26 net income | B12: 47.1
A13: P/E (statutory) | B13: =B5/B12 -> 15.41758
A14: Dividend yield | B14: =B15/B3 -> 0.030063291
A15: Dividend per share (p) | B15: 19
A17: IMPLIED VALUE PER SHARE vs EV/EBITDA MULTIPLE (FY27E)
A18: FY27E EBITDA (est., ~12% rev growth, margin held) | B18: 83
A20: EV/EBITDA | B20: Implied EV | C20: Equity value | D20: Value/share (p)
A21: 8.7 | B21: =$B$18*A21 -> 722.1 | C21: =B21-$B$6 -> 804.1 | D21: =C21/$B$4*100 -> 699.82594
A22: 10 | B22: =$B$18*A22 -> 830 | C22: =B22-$B$6 -> 912 | D22: =C22/$B$4*100 -> 793.73368
A23: 11 | B23: =$B$18*A23 -> 913 | C23: =B23-$B$6 -> 995 | D23: =C23/$B$4*100 -> 865.97041
A24: 13 | B24: =$B$18*A24 -> 1079 | C24: =B24-$B$6 -> 1161 | D24: =C24/$B$4*100 -> 1010.4439
A26: Spot price 632p. Even at 8.7x on FY27 numbers the stock is ~700p; base-case 10x = ~794p. Britvic was acquired at ~13x.
A27: Peer benchmark: Britvic / Carlsberg (2024) ~13x EV/EBITDA. A.G. Barr trades at 8.7x with net cash and stronger guided growth.
A29: PRICE TARGET (p) - ~10x FY27E EBITDA, in line with consensus ~784p | B29: 785

Sheet Thesis & Risks
A1: INVESTMENT THESIS, CATALYSTS & RISKS
A3: THESIS (BUY, target 785p, ~24% upside, 12m)
A4: - A.G. Barr is a net-cash, brand-led UK soft-drinks company (IRN-BRU, Rubicon, Boost, FUNKIN) growing earnings at a double-digit rate but priced like a mature staple at 8.7x EV/EBITDA.
A5: - FY26 delivered revenue +4.0% to GBP 437.3m, adjusted operating margin +120bps to 14.8%, and net income +19% to GBP 47.1m - evidence the portfolio reshaping (Boost, Rubicon) and pricing are working.
A6: - Management guides to 'elevated low-double-digit' revenue growth in FY27. On FY27E EBITDA of ~GBP 83m, a re-rating to 10x EV/EBITDA (still below the Britvic take-out) implies ~794p.
A8: CATALYSTS
A9: - Continued momentum in Boost and Rubicon; margin expansion delivering ahead of guidance.
A10: - Capital return / M&A: net cash of ~GBP 82m supports buybacks or bolt-on acquisitions.
A11: - Sector consolidation: post-Britvic, branded UK soft-drinks assets are scarce - scarcity/bid optionality.
A12: - Earnings upgrades if double-digit guidance is met or beaten.
A14: RISKS (and what would change the view)
A15: - Input-cost inflation (sugar, aluminium, energy) compressing the margin gains - watch gross margin.
... A19: - Sell discipline: thesis breaks if FY27 revenue growth slips to low-single-digits or margin reverses.
