Workbook

Sheet Dashboard
B2: FINSBURY FOOD GROUP PLC - Operating Model & DCF Valuation
B3: Equity research case study | Prepared by Jewel Thomas | GBP millions unless stated | FY2019A - FY2026E
B5: FY23 REVENUE | F5: FY23 ADJ. EBITDA | J5: DCF VALUE / SHARE | N5: UPSIDE vs 110p OFFER | Y5: PV explicit FCF | Z5: =SUM('DCF Valuation'!B18:D18) -> 38.87401
B6: ='Income Statement'!F4 -> 413.7 | F6: ='Income Statement'!F6 -> 31.3 | J6: ='DCF Valuation'!B27 -> 162.43016 | N6: ='DCF Valuation'!E24 -> 0.47663782 | Y6: PV terminal value | Z6: ='DCF Valuation'!E18 -> 194.82221
B7: ='Income Statement'!F5 -> 0.15947309 | F7: ='Income Statement'!F6/'Income Statement'!E6-1 -> 0.090592334 | J7: ='DCF Valuation'!B28 -> 7.4663329 | N7: vs 2023 take-private | Y7: Enterprise value | Z7: ='DCF Valuation'!B22 -> 233.69622
Y8: Less net debt | Z8: ='DCF Valuation'!B23 -> -21.4
B9: REVENUE & ADJ. EBITDA TRAJECTORY | J9: VALUATION BRIDGE (GBP m) | Y9: Equity value | Z9: ='DCF Valuation'!B24 -> 212.29622
B27: VALUATION SUMMARY (DCF base case)
B28: Enterprise value (GBP m) | G28: ='DCF Valuation'!B22 -> 233.69622
B29: Less: net bank debt (GBP m) | G29: ='DCF Valuation'!B23 -> -21.4
B30: Equity value (GBP m) | G30: ='DCF Valuation'!B24 -> 212.29622
B31: Value per share (pence) | G31: ='DCF Valuation'!B27 -> 162.43016
B32: WACC | G32: ='DCF Valuation'!B10 -> 0.08476
B33: Terminal growth | G33: =Assumptions!B21 -> 0.02
B34: Implied EV / FY23 EBITDA | G34: ='DCF Valuation'!B28 -> 7.4663329
B35: DBAY take-private (pence) | G35: ='DCF Valuation'!E21 -> 110
B36: Implied upside vs offer | G36: ='DCF Valuation'!E24 -> 0.47663782
B38: Full assumptions, statements and sensitivity grid on the following tabs. Reported figures in blue; estimates in black.

Sheet Read Me
B2: FINSBURY FOOD GROUP PLC
B3: Integrated Operating Model & DCF Valuation
B4: Prepared by Jewel Thomas | Portfolio analysis | Units: £ millions unless stated
B7: PURPOSE
B8: A demonstration equity model: three linked statements (income statement, cash flow, condensed balance sheet) feeding a discounted-cash-flow valuation of Finsbury Food Group, a UK speciality bakery manufacturer.
B11: DATA INTEGRITY — PLEASE READ
B12: This is an analyst's model, not a copy of the company's accounts.
B14: Reported figures (BLUE text)
B15: Revenue, adjusted EBITDA, adjusted profit before tax, net bank debt, gross margin and dividend per share are taken from Finsbury Food Group's published annual reports and full-year results (FY2019–FY2023). Each carries a cell comment citing the source.
B17: Estimates (BLACK / driver-based)
B18: All other line items, the FY2020 EBITDA split, and every forecast year (FY2024E–FY2026E) are analyst estimates built from the stated assumptions on the 'Assumptions' tab. They are illustrative of methodology, not guidance.
B20: Condensed balance sheet
... B37: For portfolio / educational purposes only. Not investment advice and not affiliated with or endorsed by Finsbury Food Group.

Sheet Assumptions
A1: ASSUMPTIONS & DRIVERS
A2: Blue = input you can change for scenarios. Black = calculated.
A3: £ millions | B3: FY2019A | C3: FY2020A | D3: FY2021A | E3: FY2022A | F3: FY2023A | G3: FY2024E | H3: FY2025E | I3: FY2026E
A4: Revenue (reported) | B4: 315.3 | C4: 306.3 | D4: 313.3 | E4: 356.8 | F4: 413.7
A5: Adjusted EBITDA (reported) | B5: 25.5 | C5: 21 | D5: 26.9 | E5: 28.7 | F5: 31.3
A6: Revenue growth % (forecast) | C6: =C4/B4-1 -> -0.028544244 | D6: =D4/C4-1 -> 0.022853412 | E6: =E4/D4-1 -> 0.13884456 | F6: =F4/E4-1 -> 0.15947309 | G6: 0.03 | H6: 0.035 | I6: 0.04
A7: EBITDA margin % (forecast) | B7: =B5/B4 -> 0.080875357 | C7: =C5/C4 -> 0.068560235 | D7: =D5/D4 -> 0.085860198 | E7: =E5/E4 -> 0.08043722 | F7: =F5/F4 -> 0.07565869 | G7: 0.076 | H7: 0.076 | I7: 0.076
A8: D&A as % of revenue | B8: 0.026 | C8: =$B$8 -> 0.026 | D8: =$B$8 -> 0.026 | E8: =$B$8 -> 0.026 | F8: =$B$8 -> 0.026 | G8: =$B$8 -> 0.026 | H8: =$B$8 -> 0.026 | I8: =$B$8 -> 0.026 | K8: Analyst estimate: ties FY23 adj EBITDA £31.3m to adj PBT £17.7m with net finance ~£2.8m.
A9: Capex as % of revenue | B9: 0.03 | C9: =$B$9 -> 0.03 | D9: =$B$9 -> 0.03 | E9: =$B$9 -> 0.03 | F9: =$B$9 -> 0.03 | G9: =$B$9 -> 0.03 | H9: =$B$9 -> 0.03 | I9: =$B$9 -> 0.03 | K9: Analyst estimate (maintenance + capacity).
A10: Net working capital as % of revenue | B10: 0.015 | C10: =$B$10 -> 0.015 | D10: =$B$10 -> 0.015 | E10: =$B$10 -> 0.015 | F10: =$B$10 -> 0.015 | G10: =$B$10 -> 0.015 | H10: =$B$10 -> 0.015 | I10: =$B$10 -> 0.015 | K10: Analyst estimate; bakery-to-retail supplier terms keep NWC modest.
A11: Net finance cost (% of opening net debt) | B11: 0.06 | C11: =$B$11 -> 0.06 | D11: =$B$11 -> 0.06 | E11: =$B$11 -> 0.06 | F11: =$B$11 -> 0.06 | G11: =$B$11 -> 0.06 | H11: =$B$11 -> 0.06 | I11: =$B$11 -> 0.06 | K11: Analyst estimate of blended borrowing cost.
A12: Effective tax rate | B12: 0.22 | C12: =$B$12 -> 0.22 | D12: =$B$12 -> 0.22 | E12: =$B$12 -> 0.22 | F12: =$B$12 -> 0.22 | G12: =$B$12 -> 0.22 | H12: =$B$12 -> 0.22 | I12: =$B$12 -> 0.22 | K12: UK corporation tax basis (25% headline; reliefs).
A13: Dividend payout (% of net income) | B13: 0.3 | C13: =$B$13 -> 0.3 | D13: =$B$13 -> 0.3 | E13: =$B$13 -> 0.3 | F13: =$B$13 -> 0.3 | G13: =$B$13 -> 0.3 | H13: =$B$13 -> 0.3 | I13: =$B$13 -> 0.3 | K13: Analyst estimate; FY23 full-year DPS 2.60p.
A15: VALUATION INPUTS (DCF)
A16: Risk-free rate | B16: 0.042 | K16: UK 10y gilt ~ assumption.
A17: Equity risk premium | B17: 0.055 | K17: Long-run UK ERP assumption.
A18: Beta (re-levered) | B18: 0.95 | K18: Defensive food sector; analyst estimate.
A19: Cost of debt (pre-tax) | B19: 0.06 | K19: Blended borrowing cost.
A20: Target debt / (debt+equity) | B20: 0.2 | K20: Modest leverage (0.7x EBITDA).
A21: Terminal growth rate | B21: 0.02 | K21: ~ long-run UK nominal GDP/inflation.
A22: Shares in issue (millions) | B22: 130.7 | K22: FFG shares outstanding ~130.7m (pre take-private).
A23: Net bank debt at valuation date (FY2023A) | B23: 21.4 | K23: Reported FY23 net bank debt (excl. IFRS16).

Sheet Income Statement
A1: INCOME STATEMENT (adjusted / underlying basis, £m)
A3: £ millions | B3: FY2019A | C3: FY2020A | D3: FY2021A | E3: FY2022A | F3: FY2023A | G3: FY2024E | H3: FY2025E | I3: FY2026E
A4: Revenue | B4: =Assumptions!B4 -> 315.3 | C4: =Assumptions!C4 -> 306.3 | D4: =Assumptions!D4 -> 313.3 | E4: =Assumptions!E4 -> 356.8 | F4: =Assumptions!F4 -> 413.7 | G4: =F4*(1+Assumptions!G6) -> 426.111 | H4: =G4*(1+Assumptions!H6) -> 441.02488 | I4: =H4*(1+Assumptions!I6) -> 458.66588
A5: growth % | C5: =C4/B4-1 -> -0.028544244 | D5: =D4/C4-1 -> 0.022853412 | E5: =E4/D4-1 -> 0.13884456 | F5: =F4/E4-1 -> 0.15947309 | G5: =G4/F4-1 -> 0.03 | H5: =H4/G4-1 -> 0.035 | I5: =I4/H4-1 -> 0.04
A6: Adjusted EBITDA | B6: =Assumptions!B5 -> 25.5 | C6: =Assumptions!C5 -> 21 | D6: =Assumptions!D5 -> 26.9 | E6: =Assumptions!E5 -> 28.7 | F6: =Assumptions!F5 -> 31.3 | G6: =G4*Assumptions!G7 -> 32.384436 | H6: =H4*Assumptions!H7 -> 33.517891 | I6: =I4*Assumptions!I7 -> 34.858607
A7: EBITDA margin % | B7: =B6/B4 -> 0.080875357 | C7: =C6/C4 -> 0.068560235 | D7: =D6/D4 -> 0.085860198 | E7: =E6/E4 -> 0.08043722 | F7: =F6/F4 -> 0.07565869 | G7: =G6/G4 -> 0.076 | H7: =H6/H4 -> 0.076 | I7: =I6/I4 -> 0.076
A8: Depreciation & amortisation | B8: =-B4*Assumptions!B8 -> -8.1978 | C8: =-C4*Assumptions!C8 -> -7.9638 | D8: =-D4*Assumptions!D8 -> -8.1458 | E8: =-E4*Assumptions!E8 -> -9.2768 | F8: =-F4*Assumptions!F8 -> -10.7562 | G8: =-G4*Assumptions!G8 -> -11.078886 | H8: =-H4*Assumptions!H8 -> -11.466647 | I8: =-I4*Assumptions!I8 -> -11.925313
A9: Adjusted EBIT (operating profit) | B9: =B6+B8 -> 17.3022 | C9: =C6+C8 -> 13.0362 | D9: =D6+D8 -> 18.7542 | E9: =E6+E8 -> 19.4232 | F9: =F6+F8 -> 20.5438 | G9: =G6+G8 -> 21.30555 | H9: =H6+H8 -> 22.051244 | I9: =I6+I8 -> 22.933294
A10: EBIT margin % | B10: =B9/B4 -> 0.054875357 | C10: =C9/C4 -> 0.042560235 | D10: =D9/D4 -> 0.059860198 | E10: =E9/E4 -> 0.05443722 | F10: =F9/F4 -> 0.04965869 | G10: =G9/G4 -> 0.05 | H10: =H9/H4 -> 0.05 | I10: =I9/I4 -> 0.05
A11: Net finance costs | B11: =-Assumptions!B11*'Balance Sheet'!B9 -> -2.136 | C11: =-Assumptions!C11*'Balance Sheet'!B9 -> -2.136 | D11: =-Assumptions!D11*'Balance Sheet'!C9 -> -1.8 | E11: =-Assumptions!E11*'Balance Sheet'!D9 -> -0.786 | F11: =-Assumptions!F11*'Balance Sheet'!E9 -> -1.236 | G11: =-Assumptions!G11*'Balance Sheet'!F9 -> -1.284 | H11: =-Assumptions!H11*'Balance Sheet'!G9 -> -0.74153056 | I11: =-Assumptions!I11*'Balance Sheet'!H9 -> -0.16269281
A12: Adjusted profit before tax | B12: =B9+B11 -> 15.1662 | C12: =C9+C11 -> 10.9002 | D12: =D9+D11 -> 16.9542 | E12: =E9+E11 -> 18.6372 | F12: =F9+F11 -> 19.3078 | G12: =G9+G11 -> 20.02155 | H12: =H9+H11 -> 21.309714 | I12: =I9+I11 -> 22.770601
A13: reported adj PBT (cross-check) | C13: 13.9 | E13: 17 | F13: 17.7
A14: Taxation | B14: =-B12*Assumptions!B12 -> -3.336564 | C14: =-C12*Assumptions!C12 -> -2.398044 | D14: =-D12*Assumptions!D12 -> -3.729924 | E14: =-E12*Assumptions!E12 -> -4.100184 | F14: =-F12*Assumptions!F12 -> -4.247716 | G14: =-G12*Assumptions!G12 -> -4.404741 | H14: =-H12*Assumptions!H12 -> -4.688137 | I14: =-I12*Assumptions!I12 -> -5.0095323
A15: Net income (underlying) | B15: =B12+B14 -> 11.829636 | C15: =C12+C14 -> 8.502156 | D15: =D12+D14 -> 13.224276 | E15: =E12+E14 -> 14.537016 | F15: =F12+F14 -> 15.060084 | G15: =G12+G14 -> 15.616809 | H15: =H12+H14 -> 16.621577 | I15: =I12+I14 -> 17.761069
A16: Dividends | B16: =-B15*Assumptions!B13 -> -3.5488908 | C16: =-C15*Assumptions!C13 -> -2.5506468 | D16: =-D15*Assumptions!D13 -> -3.9672828 | E16: =-E15*Assumptions!E13 -> -4.3611048 | F16: =-F15*Assumptions!F13 -> -4.5180252 | G16: =-G15*Assumptions!G13 -> -4.6850427 | H16: =-H15*Assumptions!H13 -> -4.986473 | I16: =-I15*Assumptions!I13 -> -5.3283207
A17: Retained earnings | B17: =B15+B16 -> 8.2807452 | C17: =C15+C16 -> 5.9515092 | D17: =D15+D16 -> 9.2569932 | E17: =E15+E16 -> 10.175911 | F17: =F15+F16 -> 10.542059 | G17: =G15+G16 -> 10.931766 | H17: =H15+H16 -> 11.635104 | I17: =I15+I16 -> 12.432748

Sheet Cash Flow
A1: CASH FLOW & FREE CASH FLOW (£m)
A3: £ millions | B3: FY2019A | C3: FY2020A | D3: FY2021A | E3: FY2022A | F3: FY2023A | G3: FY2024E | H3: FY2025E | I3: FY2026E
A4: Adjusted EBIT | B4: ='Income Statement'!B9 -> 17.3022 | C4: ='Income Statement'!C9 -> 13.0362 | D4: ='Income Statement'!D9 -> 18.7542 | E4: ='Income Statement'!E9 -> 19.4232 | F4: ='Income Statement'!F9 -> 20.5438 | G4: ='Income Statement'!G9 -> 21.30555 | H4: ='Income Statement'!H9 -> 22.051244 | I4: ='Income Statement'!I9 -> 22.933294
A5: Less: cash tax on EBIT | B5: =-B4*Assumptions!B12 -> -3.806484 | C5: =-C4*Assumptions!C12 -> -2.867964 | D5: =-D4*Assumptions!D12 -> -4.125924 | E5: =-E4*Assumptions!E12 -> -4.273104 | F5: =-F4*Assumptions!F12 -> -4.519636 | G5: =-G4*Assumptions!G12 -> -4.687221 | H5: =-H4*Assumptions!H12 -> -4.8512737 | I5: =-I4*Assumptions!I12 -> -5.0453247
A6: Add: depreciation & amortisation | B6: =-'Income Statement'!B8 -> 8.1978 | C6: =-'Income Statement'!C8 -> 7.9638 | D6: =-'Income Statement'!D8 -> 8.1458 | E6: =-'Income Statement'!E8 -> 9.2768 | F6: =-'Income Statement'!F8 -> 10.7562 | G6: =-'Income Statement'!G8 -> 11.078886 | H6: =-'Income Statement'!H8 -> 11.466647 | I6: =-'Income Statement'!I8 -> 11.925313
A7: Net working capital (level) | B7: ='Income Statement'!B4*Assumptions!B10 -> 4.7295 | C7: ='Income Statement'!C4*Assumptions!C10 -> 4.5945 | D7: ='Income Statement'!D4*Assumptions!D10 -> 4.6995 | E7: ='Income Statement'!E4*Assumptions!E10 -> 5.352 | F7: ='Income Statement'!F4*Assumptions!F10 -> 6.2055 | G7: ='Income Statement'!G4*Assumptions!G10 -> 6.391665 | H7: ='Income Statement'!H4*Assumptions!H10 -> 6.6153733 | I7: ='Income Statement'!I4*Assumptions!I10 -> 6.8799882
A8: Less: increase in NWC | B8: =0 -> 0 | C8: =-(C7-B7) -> 0.135 | D8: =-(D7-C7) -> -0.105 | E8: =-(E7-D7) -> -0.6525 | F8: =-(F7-E7) -> -0.8535 | G8: =-(G7-F7) -> -0.186165 | H8: =-(H7-G7) -> -0.22370828 | I8: =-(I7-H7) -> -0.26461493
A9: Less: capital expenditure | B9: =-'Income Statement'!B4*Assumptions!B9 -> -9.459 | C9: =-'Income Statement'!C4*Assumptions!C9 -> -9.189 | D9: =-'Income Statement'!D4*Assumptions!D9 -> -9.399 | E9: =-'Income Statement'!E4*Assumptions!E9 -> -10.704 | F9: =-'Income Statement'!F4*Assumptions!F9 -> -12.411 | G9: =-'Income Statement'!G4*Assumptions!G9 -> -12.78333 | H9: =-'Income Statement'!H4*Assumptions!H9 -> -13.230747 | I9: =-'Income Statement'!I4*Assumptions!I9 -> -13.759976
A10: Unlevered free cash flow (FCFF) | B10: =B4+B5+B6+B8+B9 -> 12.234516 | C10: =C4+C5+C6+C8+C9 -> 9.078036 | D10: =D4+D5+D6+D8+D9 -> 13.270076 | E10: =E4+E5+E6+E8+E9 -> 13.070396 | F10: =F4+F5+F6+F8+F9 -> 13.515864 | G10: =G4+G5+G6+G8+G9 -> 14.72772 | H10: =H4+H5+H6+H8+H9 -> 15.212163 | I10: =I4+I5+I6+I8+I9 -> 15.788691
A12: Less: net finance costs (after tax) | B12: ='Income Statement'!B11*(1-Assumptions!B12) -> -1.66608 | C12: ='Income Statement'!C11*(1-Assumptions!C12) -> -1.66608 | D12: ='Income Statement'!D11*(1-Assumptions!D12) -> -1.404 | E12: ='Income Statement'!E11*(1-Assumptions!E12) -> -0.61308 | F12: ='Income Statement'!F11*(1-Assumptions!F12) -> -0.96408 | G12: ='Income Statement'!G11*(1-Assumptions!G12) -> -1.00152 | H12: ='Income Statement'!H11*(1-Assumptions!H12) -> -0.57839384 | I12: ='Income Statement'!I11*(1-Assumptions!I12) -> -0.12690039
A13: Less: dividends paid | B13: ='Income Statement'!B16 -> -3.5488908 | C13: ='Income Statement'!C16 -> -2.5506468 | D13: ='Income Statement'!D16 -> -3.9672828 | E13: ='Income Statement'!E16 -> -4.3611048 | F13: ='Income Statement'!F16 -> -4.5180252 | G13: ='Income Statement'!G16 -> -4.6850427 | H13: ='Income Statement'!H16 -> -4.986473 | I13: ='Income Statement'!I16 -> -5.3283207
A14: Free cash flow to equity (after div) | B14: =B10+B12+B13 -> 7.0195452 | C14: =C10+C12+C13 -> 4.8613092 | D14: =D10+D12+D13 -> 7.8987932 | E14: =E10+E12+E13 -> 8.0962112 | F14: =F10+F12+F13 -> 8.0337588 | G14: =G10+G12+G13 -> 9.0411573 | H14: =H10+H12+H13 -> 9.6472959 | I14: =I10+I12+I13 -> 10.33347

Sheet Balance Sheet
A1: CONDENSED BALANCE SHEET — Capital Employed (£m)
A3: £ millions | B3: FY2019A | C3: FY2020A | D3: FY2021A | E3: FY2022A | F3: FY2023A | G3: FY2024E | H3: FY2025E | I3: FY2026E
A4: Net bank debt — opening | B4: 40 | C4: =B9 -> 35.6 | D4: =C9 -> 30 | E4: =D9 -> 13.1 | F4: =E9 -> 20.6 | G4: =F9 -> 21.4 | H4: =G9 -> 12.358843 | I4: =H9 -> 2.7115468
A5: Less: free cash flow to equity | B5: =-'Cash Flow'!B14 -> -7.0195452 | C5: =-'Cash Flow'!C14 -> -4.8613092 | D5: =-'Cash Flow'!D14 -> -7.8987932 | E5: =-'Cash Flow'!E14 -> -8.0962112 | F5: =-'Cash Flow'!F14 -> -8.0337588 | G5: =-'Cash Flow'!G14 -> -9.0411573 | H5: =-'Cash Flow'!H14 -> -9.6472959 | I5: =-'Cash Flow'!I14 -> -10.33347
A6: Net debt before reported overlay | B6: =B4+B5 -> 32.980455 | C6: =C4+C5 -> 30.738691 | D6: =D4+D5 -> 22.101207 | E6: =E4+E5 -> 5.0037888 | F6: =F4+F5 -> 12.566241 | G6: =G4+G5 -> 12.358843 | H6: =H4+H5 -> 2.7115468 | I6: =I4+I5 -> -7.621923
A8: Reported net debt (override, hist) | B8: 35.6 | C8: 30 | D8: 13.1 | E8: 20.6 | F8: 21.4
A9: Net bank debt — closing | B9: =B8 -> 35.6 | C9: =C8 -> 30 | D9: =D8 -> 13.1 | E9: =E8 -> 20.6 | F9: =F8 -> 21.4 | G9: =G6 -> 12.358843 | H9: =H6 -> 2.7115468 | I9: =I6 -> -7.621923
A11: Shareholders' equity — opening | B11: 95 | C11: =B13 -> 103.28075 | D11: =C13 -> 109.23225 | E11: =D13 -> 118.48925 | F11: =E13 -> 128.66516 | G11: =F13 -> 139.20722 | H11: =G13 -> 150.13898 | I11: =H13 -> 161.77409
A12: Add: retained earnings | B12: ='Income Statement'!B17 -> 8.2807452 | C12: ='Income Statement'!C17 -> 5.9515092 | D12: ='Income Statement'!D17 -> 9.2569932 | E12: ='Income Statement'!E17 -> 10.175911 | F12: ='Income Statement'!F17 -> 10.542059 | G12: ='Income Statement'!G17 -> 10.931766 | H12: ='Income Statement'!H17 -> 11.635104 | I12: ='Income Statement'!I17 -> 12.432748
A13: Shareholders' equity — closing | B13: =B11+B12 -> 103.28075 | C13: =C11+C12 -> 109.23225 | D13: =D11+D12 -> 118.48925 | E13: =E11+E12 -> 128.66516 | F13: =F11+F12 -> 139.20722 | G13: =G11+G12 -> 150.13898 | H13: =H11+H12 -> 161.77409 | I13: =I11+I12 -> 174.20684
A15: Capital employed (net debt + equity) | B15: =B9+B13 -> 138.88075 | C15: =C9+C13 -> 139.23225 | D15: =D9+D13 -> 131.58925 | E15: =E9+E13 -> 149.26516 | F15: =F9+F13 -> 160.60722 | G15: =G9+G13 -> 162.49783 | H15: =H9+H13 -> 164.48563 | I15: =I9+I13 -> 166.58491
A17: Funded by — fixed assets (PP&E + intangibles) | B17: ='Income Statement'!B4*0.55 -> 173.415 | C17: ='Income Statement'!C4*0.55 -> 168.465 | D17: ='Income Statement'!D4*0.55 -> 172.315 | E17: ='Income Statement'!E4*0.55 -> 196.24 | F17: ='Income Statement'!F4*0.55 -> 227.535 | G17: ='Income Statement'!G4*0.55 -> 234.36105 | H17: ='Income Statement'!H4*0.55 -> 242.56369 | I17: ='Income Statement'!I4*0.55 -> 252.26623
A18: Net working capital | B18: ='Cash Flow'!B7 -> 4.7295 | C18: ='Cash Flow'!C7 -> 4.5945 | D18: ='Cash Flow'!D7 -> 4.6995 | E18: ='Cash Flow'!E7 -> 5.352 | F18: ='Cash Flow'!F7 -> 6.2055 | G18: ='Cash Flow'!G7 -> 6.391665 | H18: ='Cash Flow'!H7 -> 6.6153733 | I18: ='Cash Flow'!I7 -> 6.8799882
A19: Other net assets (balancing, est.) | B19: =B15-B17-B18 -> -39.263755 | C19: =C15-C17-C18 -> -33.827246 | D19: =D15-D17-D18 -> -45.425252 | E19: =E15-E17-E18 -> -52.326841 | F19: =F15-F17-F18 -> -73.133282 | G19: =G15-G17-G18 -> -78.254888 | H19: =H15-H17-H18 -> -84.693426 | I19: =I15-I17-I18 -> -92.56131
A20: Check: composition = capital employed | B20: =B17+B18+B19-B15 -> 0 | C20: =C17+C18+C19-C15 -> 0 | D20: =D17+D18+D19-D15 -> 0 | E20: =E17+E18+E19-E15 -> 0 | F20: =F17+F18+F19-F15 -> 0 | G20: =G17+G18+G19-G15 -> 0 | H20: =H17+H18+H19-H15 -> 0 | I20: =I17+I18+I19-I15 -> 0

Sheet DCF Valuation
A1: DCF VALUATION (£m unless stated)
A3: WACC build
A4: Risk-free rate | B4: =Assumptions!B16 -> 0.042
A5: Beta x Equity risk premium | B5: =Assumptions!B18*Assumptions!B17 -> 0.05225
A6: Cost of equity | B6: =B4+B5 -> 0.09425
A7: Cost of debt (after tax) | B7: =Assumptions!B19*(1-Assumptions!B12) -> 0.0468
A8: Weight of equity | B8: =1-Assumptions!B20 -> 0.8
A9: Weight of debt | B9: =Assumptions!B20 -> 0.2
A10: WACC | B10: =B6*B8+B7*B9 -> 0.08476
A11: Terminal growth rate | B11: =Assumptions!B21 -> 0.02
A13: Discounted cash flow
B14: FY2024E | C14: FY2025E | D14: FY2026E | E14: Terminal
A15: Unlevered FCF (FCFF) | B15: ='Cash Flow'!G10 -> 14.72772 | C15: ='Cash Flow'!H10 -> 15.212163 | D15: ='Cash Flow'!I10 -> 15.788691 | E15: =D15*(1+B11)/(B10-B11) -> 248.6792
A16: Discount period (years) | B16: 1 | C16: 2 | D16: 3 | E16: =D16 -> 3
A17: Discount factor @ WACC | B17: =1/(1+$B$10)^B16 -> 0.9218629 | C17: =1/(1+$B$10)^C16 -> 0.84983121 | D17: =1/(1+$B$10)^D16 -> 0.78342786 | E17: =1/(1+$B$10)^E16 -> 0.78342786
A18: Present value | B18: =B15*B17 -> 13.576939 | C18: =C15*C17 -> 12.927771 | D18: =D15*D17 -> 12.3693 | E18: =E15*E17 -> 194.82221
A20: Sum of PV of explicit FCF (FY24-26) | B20: =SUM(B18:D18) -> 38.87401 | D20: REALITY CHECK vs 2023 TAKE-PRIVATE
A21: PV of terminal value | B21: =E18 -> 194.82221 | D21: DBAY offer price (Sep 2023), pence | E21: 110
A22: Enterprise value | B22: =B20+B21 -> 233.69622 | D22: Prior close pre-bid, pence | E22: 89
A23: Less: net bank debt (FY2023A) | B23: =-Assumptions!B23 -> -21.4 | D23: Model implied value, pence | E23: =B27 -> 162.43016
A24: Equity value | B24: =B22+B23 -> 212.29622 | D24: Implied upside vs offer | E24: =B27/E21-1 -> 0.47663782
A25: Shares in issue (m) | B25: =Assumptions!B22 -> 130.7 | D25: Two institutional holders publicly opposed the 110p deal as undervaluing FFG — consistent with this DCF.
A26: Implied value per share (£) | B26: =B24/B25 -> 1.6243016
A27: Implied value per share (pence) | B27: =B26*100 -> 162.43016
A28: Implied EV / FY23 EBITDA | B28: =B22/Assumptions!F5 -> 7.4663329
A29: Context: Finsbury was taken private in Nov 2023 (DBAY Advisors). This DCF is an independent estimate for portfolio demonstration.
A32: SENSITIVITY — implied value per share (pence)
A33: WACC (down) / terminal g (across)
B34: g = | C34: 0.015 | D34: 0.02 | E34: 0.025
B35: 0.08 | C35: =($B$15/(1+$B35)^1+$C$15/(1+$B35)^2+$D$15/(1+$B35)^3+$D$15*(1+C$34)/($B35-C$34)/(1+$B35)^3-Assumptions!$B$23)/Assumptions!$B$22*100 -> 163.37328 | D35: =($B$15/(1+$B35)^1+$C$15/(1+$B35)^2+$D$15/(1+$B35)^3+$D$15*(1+D$34)/($B35-D$34)/(1+$B35)^3-Assumptions!$B$23)/Assumptions!$B$22*100 -> 176.65115 | E35: =($B$15/(1+$B35)^1+$C$15/(1+$B35)^2+$D$15/(1+$B35)^3+$D$15*(1+E$34)/($B35-E$34)/(1+$B35)^3-Assumptions!$B$23)/Assumptions!$B$22*100 -> 192.34318
B36: 0.085 | C36: =($B$15/(1+$B36)^1+$C$15/(1+$B36)^2+$D$15/(1+$B36)^3+$D$15*(1+C$34)/($B36-C$34)/(1+$B36)^3-Assumptions!$B$23)/Assumptions!$B$22*100 -> 150.49192 | D36: =($B$15/(1+$B36)^1+$C$15/(1+$B36)^2+$D$15/(1+$B36)^3+$D$15*(1+D$34)/($B36-D$34)/(1+$B36)^3-Assumptions!$B$23)/Assumptions!$B$22*100 -> 161.7683 | E36: =($B$15/(1+$B36)^1+$C$15/(1+$B36)^2+$D$15/(1+$B36)^3+$D$15*(1+E$34)/($B36-E$34)/(1+$B36)^3-Assumptions!$B$23)/Assumptions!$B$22*100 -> 174.92408
B37: 0.09 | C37: =($B$15/(1+$B37)^1+$C$15/(1+$B37)^2+$D$15/(1+$B37)^3+$D$15*(1+C$34)/($B37-C$34)/(1+$B37)^3-Assumptions!$B$23)/Assumptions!$B$22*100 -> 139.32857 | D37: =($B$15/(1+$B37)^1+$C$15/(1+$B37)^2+$D$15/(1+$B37)^3+$D$15*(1+D$34)/($B37-D$34)/(1+$B37)^3-Assumptions!$B$23)/Assumptions!$B$22*100 -> 149.01198 | E37: =($B$15/(1+$B37)^1+$C$15/(1+$B37)^2+$D$15/(1+$B37)^3+$D$15*(1+E$34)/($B37-E$34)/(1+$B37)^3-Assumptions!$B$23)/Assumptions!$B$22*100 -> 160.18515
B38: 0.095 | C38: =($B$15/(1+$B38)^1+$C$15/(1+$B38)^2+$D$15/(1+$B38)^3+$D$15*(1+C$34)/($B38-C$34)/(1+$B38)^3-Assumptions!$B$23)/Assumptions!$B$22*100 -> 129.56109 | D38: =($B$15/(1+$B38)^1+$C$15/(1+$B38)^2+$D$15/(1+$B38)^3+$D$15*(1+D$34)/($B38-D$34)/(1+$B38)^3-Assumptions!$B$23)/Assumptions!$B$22*100 -> 137.95687 | E38: =($B$15/(1+$B38)^1+$C$15/(1+$B38)^2+$D$15/(1+$B38)^3+$D$15*(1+E$34)/($B38-E$34)/(1+$B38)^3-Assumptions!$B$23)/Assumptions!$B$22*100 -> 147.55205
B39: 0.1 | C39: =($B$15/(1+$B39)^1+$C$15/(1+$B39)^2+$D$15/(1+$B39)^3+$D$15*(1+C$34)/($B39-C$34)/(1+$B39)^3-Assumptions!$B$23)/Assumptions!$B$22*100 -> 120.94315 | D39: =($B$15/(1+$B39)^1+$C$15/(1+$B39)^2+$D$15/(1+$B39)^3+$D$15*(1+D$34)/($B39-D$34)/(1+$B39)^3-Assumptions!$B$23)/Assumptions!$B$22*100 -> 128.284 | E39: =($B$15/(1+$B39)^1+$C$15/(1+$B39)^2+$D$15/(1+$B39)^3+$D$15*(1+E$34)/($B39-E$34)/(1+$B39)^3-Assumptions!$B$23)/Assumptions!$B$22*100 -> 136.60362
