Workbook

Sheet Dashboard
B2: FINSBURY FOOD GROUP - FP&A: Budget vs Actual (FY2023) | X2: Line | Y2: Plan | Z2: Actual
B3: Variance pack | Prepared by Jewel Thomas | GBP millions | Actuals per reported FY2023; plan analyst-constructed | X3: Revenue | Y3: ='Variance Analysis'!B4 -> 405 | Z3: ='Variance Analysis'!C4 -> 413.7
X4: Gross profit | Y4: ='Variance Analysis'!B6 -> 127.6 | Z4: ='Variance Analysis'!C6 -> 124.1
B5: REVENUE vs PLAN | F5: ADJ. EBITDA vs PLAN | J5: EBITDA VARIANCE | N5: GROSS MARGIN vs PLAN | X5: Adj EBITDA | Y5: ='Variance Analysis'!B8 -> 30.5 | Z5: ='Variance Analysis'!C8 -> 31.3
B6: ='Variance Analysis'!C4 -> 413.7 | F6: ='Variance Analysis'!C8 -> 31.3 | J6: ='Variance Analysis'!D8 -> 0.8 | N6: ='Variance Analysis'!C12 -> 0.29997583
B7: ='Variance Analysis'!E4 -> 0.021481481 | F7: ='Variance Analysis'!D8 -> 0.8 | J7: ='Variance Analysis'!E8 -> 0.026229508 | N7: ='Variance Analysis'!D12 -> -0.015085901
X8: Plan EBITDA | Y8: ='Variance Analysis'!B18 -> 30.5
B9: BUDGET vs ACTUAL BY P&L LINE (GBP m) | J9: EBITDA BRIDGE: PLAN -> ACTUAL (GBP m) | X9: Volume (F) | Y9: ='Variance Analysis'!B19 -> 2.741037
X10: Margin (A) | Y10: ='Variance Analysis'!B20 -> -6.241037
X11: Overheads (F) | Y11: ='Variance Analysis'!B21 -> 4.3
X12: Actual EBITDA | Y12: ='Variance Analysis'!B22 -> 31.3
B27: VARIANCE SUMMARY (Actual vs Plan, FY2023)
B28: P&L line | C28: Plan | D28: Actual | E28: Var (GBP m) | F28: F/A
B29: Revenue | C29: ='Variance Analysis'!B4 -> 405 | D29: ='Variance Analysis'!C4 -> 413.7 | E29: ='Variance Analysis'!D4 -> 8.7 | F29: ='Variance Analysis'!F4 -> Favourable
B30: Gross profit | C30: ='Variance Analysis'!B6 -> 127.6 | D30: ='Variance Analysis'!C6 -> 124.1 | E30: ='Variance Analysis'!D6 -> -3.5 | F30: ='Variance Analysis'!F6 -> Adverse
B31: Adjusted EBITDA | C31: ='Variance Analysis'!B8 -> 30.5 | D31: ='Variance Analysis'!C8 -> 31.3 | E31: ='Variance Analysis'!D8 -> 0.8 | F31: ='Variance Analysis'!F8 -> Favourable
B32: Adjusted EBIT | C32: ='Variance Analysis'!B10 -> 20 | D32: ='Variance Analysis'!C10 -> 20.5 | E32: ='Variance Analysis'!D10 -> 0.5 | F32: ='Variance Analysis'!F10 -> Favourable
B34: Revenue beat plan, but margin missed on cost inflation; overhead control carried EBITDA ahead of plan. Full detail on Variance Analysis tab.

Sheet Read Me
B2: FINSBURY FOOD GROUP - FP&A PACK
B3: Budget vs Actual Variance Analysis & KPI Dashboard
B4: Prepared by Jewel Thomas | Portfolio analysis | GBP millions unless stated | FY2023
B6: PURPOSE
B7: A financial planning & analysis (FP&A) pack: comparing a financial plan (budget) against actual results, quantifying the variance on every P&L line, splitting the profit miss/beat into its drivers, and tracking the year quarter by quarter - the core monthly job of a commercial finance / FP&A analyst.
B9: THE STORY IT TELLS
B10: Revenue beat plan (+GBP 8.7m, +2.1%), but gross margin came in 1.5pp below plan on input-cost inflation - a GBP 6.2m adverse rate variance. Tight overhead control (+GBP 4.3m favourable) more than offset this, so adjusted EBITDA still finished GBP 0.8m ahead of plan. The lesson a business partner would flag: the beat was earned on cost discipline, not margin - watch pricing.
B12: DATA INTEGRITY
B13: Actuals are anchored to Finsbury's reported FY2023 figures. The plan/budget and the quarterly phasing are analyst-constructed, clearly flagged, and exist to demonstrate the variance technique - not to represent Finsbury's real internal budget (which is not public). Plan inputs are blue and editable on the Variance Analysis tab.
B15: HOW TO READ IT
B16: 'Dashboard' = one-page summary with KPI variances and the EBITDA bridge. 'Variance Analysis' = full plan-vs-actual by line with favourable/adverse flags. 'Quarterly Tracker' = phased budget-vs-actual through the year.
B18: METHOD NOTE
... B25: For portfolio / educational purposes only. Not investment advice; not affiliated with or endorsed by Finsbury Food Group.

Sheet Variance Analysis
A1: BUDGET vs ACTUAL - FY2023 (GBP m)
A3: P&L line | B3: Plan | C3: Actual | D3: Var (GBP m) | E3: Var % | F3: F/A
A4: Revenue | B4: 405 | C4: 413.7 | D4: =C4-B4 -> 8.7 | E4: =IF(B4=0,0,(C4-B4)/ABS(B4)) -> 0.021481481 | F4: =IF(D4>=0,"Favourable","Adverse") -> Favourable
A5: Cost of sales | B5: -277.4 | C5: -289.6 | D5: =C5-B5 -> -12.2 | E5: =IF(B5=0,0,(C5-B5)/ABS(B5)) -> -0.043979813 | F5: =IF(D5>=0,"Favourable","Adverse") -> Adverse
A6: Gross profit | B6: =B4+B5 -> 127.6 | C6: =C4+C5 -> 124.1 | D6: =C6-B6 -> -3.5 | E6: =IF(B6=0,0,(C6-B6)/ABS(B6)) -> -0.027429467 | F6: =IF(D6>=0,"Favourable","Adverse") -> Adverse
A7: Overheads (excl. D&A) | B7: -97.1 | C7: -92.8 | D7: =C7-B7 -> 4.3 | E7: =IF(B7=0,0,(C7-B7)/ABS(B7)) -> 0.044284243 | F7: =IF(D7>=0,"Favourable","Adverse") -> Favourable
A8: Adjusted EBITDA | B8: =B6+B7 -> 30.5 | C8: =C6+C7 -> 31.3 | D8: =C8-B8 -> 0.8 | E8: =IF(B8=0,0,(C8-B8)/ABS(B8)) -> 0.026229508 | F8: =IF(D8>=0,"Favourable","Adverse") -> Favourable
A9: Depreciation & amortisation | B9: -10.5 | C9: -10.8 | D9: =C9-B9 -> -0.3 | E9: =IF(B9=0,0,(C9-B9)/ABS(B9)) -> -0.028571429 | F9: =IF(D9>=0,"Favourable","Adverse") -> Adverse
A10: Adjusted EBIT | B10: =B8+B9 -> 20 | C10: =C8+C9 -> 20.5 | D10: =C10-B10 -> 0.5 | E10: =IF(B10=0,0,(C10-B10)/ABS(B10)) -> 0.025 | F10: =IF(D10>=0,"Favourable","Adverse") -> Favourable
A12: Gross margin % | B12: =B6/B4 -> 0.31506173 | C12: =C6/C4 -> 0.29997583 | D12: =C12-B12 -> -0.015085901
A13: EBITDA margin % | B13: =B8/B4 -> 0.075308642 | C13: =C8/C4 -> 0.07565869 | D13: =C13-B13 -> 0.0003500479
A15: Plan figures (blue) are editable - change them and all variances, the bridge and the dashboard update.
A17: EBITDA BRIDGE: PLAN -> ACTUAL (GBP m)
A18: Plan EBITDA | B18: =B8 -> 30.5
A19: Volume / revenue (F) | B19: =(C4-B4)*(B6/B4) -> 2.741037
A20: Gross margin rate (A) | B20: =(C6/C4-B6/B4)*C4 -> -6.241037
A21: Overhead control (F) | B21: =C7-B7 -> 4.3
A22: Actual EBITDA | B22: =C8 -> 31.3

Sheet Quarterly Tracker
A1: QUARTERLY BUDGET vs ACTUAL - FY2023 (illustrative phasing)
A3: GBP m | B3: Q1 | C3: Q2 | D3: Q3 | E3: Q4 | F3: FY
A5: Revenue
A6: Plan | B6: ='Variance Analysis'!B4*0.22 -> 89.1 | C6: ='Variance Analysis'!B4*0.24 -> 97.2 | D6: ='Variance Analysis'!B4*0.28 -> 113.4 | E6: ='Variance Analysis'!B4*0.26 -> 105.3 | F6: =SUM(B6:E6) -> 405
A7: Actual | B7: ='Variance Analysis'!C4*0.22 -> 91.014 | C7: ='Variance Analysis'!C4*0.24 -> 99.288 | D7: ='Variance Analysis'!C4*0.28 -> 115.836 | E7: ='Variance Analysis'!C4*0.26 -> 107.562 | F7: =SUM(B7:E7) -> 413.7
A8: Variance | B8: =B7-B6 -> 1.914 | C8: =C7-C6 -> 2.088 | D8: =D7-D6 -> 2.436 | E8: =E7-E6 -> 2.262 | F8: =F7-F6 -> 8.7
A10: Adjusted EBITDA
A11: Plan | B11: ='Variance Analysis'!B8*0.22 -> 6.71 | C11: ='Variance Analysis'!B8*0.24 -> 7.32 | D11: ='Variance Analysis'!B8*0.28 -> 8.54 | E11: ='Variance Analysis'!B8*0.26 -> 7.93 | F11: =SUM(B11:E11) -> 30.5
A12: Actual | B12: ='Variance Analysis'!C8*0.22 -> 6.886 | C12: ='Variance Analysis'!C8*0.24 -> 7.512 | D12: ='Variance Analysis'!C8*0.28 -> 8.764 | E12: ='Variance Analysis'!C8*0.26 -> 8.138 | F12: =SUM(B12:E12) -> 31.3
A13: Variance | B13: =B12-B11 -> 0.176 | C13: =C12-C11 -> 0.192 | D13: =D12-D11 -> 0.224 | E13: =E12-E11 -> 0.208 | F13: =F12-F11 -> 0.8
A15: Quarterly split is an illustrative seasonal phasing (H2-weighted) of the FY plan and actual. For methodology demonstration only.
