Workbook

Sheet Dashboard
B2: FIRSTGROUP PLC - Cash Flow & Working Capital Analysis | Y2: Adj EBITDA | Z2: ='Cash Flow Bridge'!C4 -> 779.8
B3: Equity research case study | Prepared by Jewel Thomas | GBP millions unless stated | FY ends late March | Reported actuals | Y3: Working capital | Z3: ='Cash Flow Bridge'!C6 -> 75.7
Y4: Other operating | Z4: ='Cash Flow Bridge'!C5+'Cash Flow Bridge'!C7+'Cash Flow Bridge'!C8+'Cash Flow Bridge'!C10 -> -27.3
B5: FY25 REVENUE | F5: CASH FROM OPERATIONS | J5: FREE CASH FLOW | N5: WORKING CAPITAL (FY25) | Y5: Cash from ops | Z5: ='Cash Flow Bridge'!C11 -> 828.2
B6: ='P&L & Returns'!D4 -> 5069 | F6: ='Cash Flow Bridge'!C11 -> 828.2 | J6: ='Cash Flow Bridge'!C22 -> 113.5 | N6: ='Cash Flow Bridge'!C6 -> 75.7
B7: ='P&L & Returns'!D4/'P&L & Returns'!C4-1 -> 0.073031329 | F7: ='Cash Flow Bridge'!C11/'Cash Flow Bridge'!B11-1 -> 0.32173635 | J7: ='Cash Flow Bridge'!C22/'Cash Flow Bridge'!B22-1 -> 1.1057514 | N7: inflow vs (106)m outflow FY24
Y8: FY2024 | Z8: ='Cash Flow Bridge'!B6 -> -106.1
B9: OPERATING CASH FLOW BRIDGE - FY25 (GBP m) | J9: WORKING CAPITAL SWING (GBP m) | Y9: FY2025 | Z9: ='Cash Flow Bridge'!C6 -> 75.7
B27: KEY METRICS (FY2025 vs FY2024)
B28: Revenue (GBP m) | G28: ='P&L & Returns'!D4 -> 5069
B29: Adjusted operating profit (GBP m) | G29: ='P&L & Returns'!D5 -> 222.8
B30: Adjusted operating margin | G30: ='P&L & Returns'!D6 -> 0.043953442
B31: Cash generated by operations (GBP m) | G31: ='Cash Flow Bridge'!C11 -> 828.2
B32: Cash conversion (OCF / Adj EBITDA) | G32: ='Working Capital'!C7 -> 1.0620672
B33: Free cash flow (GBP m) | G33: ='Cash Flow Bridge'!C22 -> 113.5
B34: Capital returned to shareholders (GBP m) | G34: =-('Cash Flow Bridge'!C19+'Cash Flow Bridge'!C20) -> 126
B35: Dividend per share (pence) | G35: ='P&L & Returns'!D14 -> 6.5
B36: Adjusted net debt/(cash) (GBP m) | G36: ='P&L & Returns'!D15 -> 86.9
B38: All figures reported actuals from FirstGroup FY2025 results. Detail and sources on the Cash Flow Bridge, Working Capital and P&L & Returns tabs.

Sheet Read Me
B2: FIRSTGROUP PLC
B3: Cash Flow & Working Capital Analysis
B4: Prepared by Jewel Thomas | Portfolio analysis | GBP millions unless stated | Financial years end late March
B6: PURPOSE
B7: A focused analysis of how a major UK transport operator (bus and rail) turns profit into cash - the operating cash-flow bridge, the swing in working capital, cash conversion, and how the cash is allocated between reinvestment and shareholder returns.
B9: WHY FIRSTGROUP
B10: Transport and rail businesses have distinctive working-capital dynamics: passenger income and government contract receipts are often collected ahead of the cost of delivering service, so working capital can be a structural source of cash - but it is volatile and contract-timing sensitive. FirstGroup is a clean case study of this.
B12: DATA INTEGRITY
B13: Unlike a forecast model, almost every figure here is reported actuals taken directly from FirstGroup's FY2025 results statement (which restates FY2024). Hardcoded reported figures are shown in blue with source notes. The only analyst-derived items are ratios (e.g. cash conversion) computed by formula from those reported figures.
B15: HEADLINE FINDINGS
B16: (1) Working capital swung from a GBP 106.1m OUTFLOW in FY2024 to a GBP 75.7m INFLOW in FY2025 - a c.GBP 182m swing, largely rail contract timing. (2) Cash generated by operations rose 32% to GBP 828.2m. (3) Free cash flow more than doubled to GBP 113.5m. (4) The group still returned GBP 126m to shareholders (dividends + buyback) and moved from net cash to modest adjusted net debt of GBP 86.9m after GBP 86.5m of acquisitions.
B18: HOW TO READ IT
... B25: For portfolio / educational purposes only. Not investment advice; not affiliated with or endorsed by FirstGroup plc.

Sheet Cash Flow Bridge
A1: OPERATING CASH FLOW BRIDGE (GBP m)
A3: GBP millions | B3: FY2024A | C3: FY2025A | D3: Change
A4: Adjusted EBITDA | B4: 746.8 | C4: 779.8 | D4: =C4-B4 -> 33
A5: Other non-cash items | B5: 13.7 | C5: 10.3 | D5: =C5-B5 -> -3.4
A6: Working capital movement | B6: -106.1 | C6: 75.7 | D6: =C6-B6 -> 181.8
A7: Movement in other provisions | B7: -27.9 | C7: -27.9 | D7: =C7-B7 -> 0
A8: (Increase)/decrease in financial assets | B8: 23.7 | C8: -1 | D8: =C8-B8 -> -24.7
A9: Settlement of FX hedge | B9: -1.1 | C9: 0 | D9: =C9-B9 -> 1.1
A10: DB pension payments vs charge | B10: -22.5 | C10: -8.7 | D10: =C10-B10 -> 13.8
A11: Cash generated by operations | B11: 626.6 | C11: 828.2 | D11: =C11-B11 -> 201.6
A12: Net capital expenditure | B12: -219.3 | C12: -156.4 | D12: =C12-B12 -> 62.9
A13: Proceeds from capital grant funding | B13: 94.8 | C13: 66.4 | D13: =C13-B13 -> -28.4
A14: Acquisitions | B14: -16.7 | C14: -86.5 | D14: =C14-B14 -> -69.8
A15: Proceeds from disposal of PP&E | B15: 42.8 | C15: 17.9 | D15: =C15-B15 -> -24.9
... A22: Free cash flow | B22: 53.9 | C22: 113.5 | D22: =C22-B22 -> 59.6
A24: All line items reported in FirstGroup FY2025 results 'movement in net debt' bridge. Free cash flow as defined by the company.

Sheet Working Capital
A1: WORKING CAPITAL & CASH CONVERSION
A3: GBP millions | B3: FY2024A | C3: FY2025A | D3: Change
A4: Working capital movement (cash) | B4: -106.1 | C4: 75.7 | D4: =C4-B4 -> 181.8
A5: Adjusted EBITDA | B5: 746.8 | C5: 779.8
A6: Cash generated by operations | B6: 626.6 | C6: 828.2
A7: Cash conversion (OCF / Adj EBITDA) | B7: =B6/B5 -> 0.8390466 | C7: =C6/C5 -> 1.0620672
A9: Revenue | B9: 4724 | C9: 5069
A10: Working capital as % of revenue | B10: =B4/B9 -> -0.02245978 | C10: =C4/C9 -> 0.014933912
A13: WHY THE SWING (c. GBP 182m FY24 to FY25):
A14: Rail operations collect passenger income and DfT contract receipts on timing that does not match the cost of running services. In FY2024 the unwind of prior balances drove a GBP 106.1m working-capital outflow; in FY2025 contract timing reversed into a GBP 75.7m inflow.
A16: STRUCTURAL POINT:
A17: Deferred income (season tickets, advance fares, contract receipts) means a transport/rail group can run with negative working capital - customers and government effectively pre-fund operations. This is a genuine, recurring source of cash, but it is volatile and reverses as contracts transition (the DfT is moving train operating companies into public ownership).
A19: FORWARD FLAG (company guidance):
A20: FirstGroup expects a c. GBP 120m cash inflow over three years from April 2025 as DfT contracts transition - a working-capital / cash-timing item, not trading profit.

Sheet P&L & Returns
A1: PROFITABILITY & CAPITAL ALLOCATION (GBP m)
A3: GBP millions | B3: FY2023A | C3: FY2024A | D3: FY2025A
A4: Revenue | B4: 4756 | C4: 4724 | D4: 5069
A5: Adjusted operating profit | B5: 161 | C5: 204.3 | D5: 222.8
A6: Adjusted operating margin | B6: =B5/B4 -> 0.033851976 | C6: =C5/C4 -> 0.043247248 | D6: =D5/D4 -> 0.043953442
A8: CAPITAL ALLOCATION (FY2024 / FY2025)
A9: Free cash flow | C9: 53.9 | D9: 113.5
A10: Net capital expenditure | C10: -219.3 | D10: -156.4
A11: Acquisitions | C11: -16.7 | D11: -86.5
A12: Share buyback | C12: -117.6 | D12: -91.8
A13: External dividends | C13: -29.5 | D13: -34.2
A14: Dividend per share (pence) | C14: 5.5 | D14: 6.5
A15: Adjusted net debt/(cash) | C15: -64.1 | D15: 86.9
A17: Adjusted net debt/(cash): negative = net cash. FY24 net cash GBP 64.1m; FY25 net debt GBP 86.9m after GBP 86.5m acquisitions. Source: FirstGroup plc FY2025 results (52 weeks to 29 Mar 2025), released 10 Jun 2025; firstgroupplc.com.
